rl/__init__.py
rl/callbacks.py
rl/core.py
rl/memory.py
rl/policy.py
rl/processors.py
rl/random.py
rl/util.py
rl/agents/__init__.py
rl/agents/cem.py
rl/agents/ddpg.py
rl/agents/dqn.py
rl/agents/sarsa.py
rl/common/__init__.py
rl/common/cmd_util.py
rl/common/misc_util.py
rl/common/tile_images.py
rl/common/vec_env/__init__.py
rl/common/vec_env/subproc_env_vec.py
tests/__init__.py
tests/rl/__init__.py
tests/rl/test_core.py
tests/rl/test_memory.py
tests/rl/test_util.py
tests/rl/util.py
tests/rl/agents/__init__.py
tests/rl/agents/test_cem.py
tests/rl/agents/test_ddpg.py
tests/rl/agents/test_dqn.py
utils/__init__.py
utils/gym/__init__.py
utils/gym/prng.py
utils/gym/envs/__init__.py
utils/gym/envs/twoRoundDeterministicRewardEnv.py
utils/gym/spaces/__init__.py
utils/gym/spaces/discrete.py
keras_rl2-1.0.5.dist-info/LICENSE
keras_rl2-1.0.5.dist-info/METADATA
keras_rl2-1.0.5.dist-info/WHEEL
keras_rl2-1.0.5.dist-info/top_level.txt
keras_rl2-1.0.5.dist-info/RECORD
